sdpdump/__init__.py
sdpdump/sdpdump.py
sdpdump-1.0.0.dist-info/METADATA
sdpdump-1.0.0.dist-info/WHEEL
sdpdump-1.0.0.dist-info/entry_points.txt
sdpdump-1.0.0.dist-info/top_level.txt
sdpdump-1.0.0.dist-info/RECORD
