Metadata-Version: 2.4
Name: sdpdump
Version: 1.0.0
Summary: Tool for extracting audio from konami sdp files.
Home-page: http://github.com/camprevail/sdpdump
Author: Cammy
Author-email: 
License: MIT
Keywords: sdp, sdpdump, konami
Classifier: Programming Language :: Python :: 3
Classifier: License :: OSI Approved :: MIT License
Classifier: Operating System :: OS Independent
Requires-Dist: numba
Requires-Dist: setuptools
Dynamic: author
Dynamic: classifier
Dynamic: description
Dynamic: description-content-type
Dynamic: home-page
Dynamic: keywords
Dynamic: license
Dynamic: requires-dist
Dynamic: summary
